monk_cmd/__init__.py
monk_cmd/cmd.py
monk_cmd-0.1.0.dist-info/METADATA
monk_cmd-0.1.0.dist-info/WHEEL
monk_cmd-0.1.0.dist-info/entry_points.txt
monk_cmd-0.1.0.dist-info/top_level.txt
monk_cmd-0.1.0.dist-info/RECORD
